{
  "name": "Reality Patch",
  "img": "modules/cybermancy/assets/icons/domains/reality-patch.webp",
  "type": "Ability",
  "system": {
    "description": "“If you can code it, you can unbreak it.” Spend 1 Hope to temporarily stabilize or rewrite corrupted digital space. Remove one ongoing Environment Digital effect.",
    "domain": "circuit",
    "recallCost": 0,
    "level": 8,
    "type": "spell",
    "actions": [],
    "resource": null,
    "inVault": false,
    "theme": "Environment",
    "effect": "Spend 1 Hope to temporarily stabilize or rewrite corrupted digital space. Remove one ongoing Environment Digital effect.",
    "blurb": "“If you can code it, you can unbreak it.”"
  },
  "effects": []
}