{
  "name": "Deep search",
  "img": "modules/cybermancy/assets/icons/domains/circuit/deep-search.webp",
  "type": "domainCard",
  "system": {
    "description": "“The Grid whispers, if you know how to listen.” Spend 2 Hope to know something about an enemy.  As the GM up to 3 yes/no questions.",
    "domain": "circuits",
    "recallCost": 0,
    "level": 3,
    "type": "ability",
    "actions": [],
    "resource": null,
    "inVault": false,
    "theme": "Role playing",
    "effect": "Spend 2 Hope to know something about an enemy.  As the GM up to 3 yes/no questions.",
    "blurb": "“The Grid whispers, if you know how to listen.”"
  },
  "effects": []
}