{
  "name": "Legendary Monofilament Whip",
  "type": "weapon",
  "img": "modules/cybermancy/assets/icons/weapons/legendary-monofilament-whip.webp",
  "system": {
    "description": "The apex of weaponized filaments, capable of cutting through armor, steel, or reality itself.",
    "tier": 4,
    "equipped": false,
    "secondary": false,
    "burden": "oneHanded",
    "attack": {
      "name": "Attack",
      "img": "modules/cybermancy/assets/icons/weapons/legendary-monofilament-whip.webp",
      "systemPath": "attack",
      "type": "attack",
      "range": "veryClose",
      "target": {
        "type": "any",
        "amount": 1
      },
      "roll": {
        "trait": "finesse",
        "type": "attack",
        "difficulty": null,
        "bonus": null,
        "advState": "neutral",
        "diceRolling": {
          "multiplier": "prof",
          "flatMultiplier": 1,
          "dice": "d6"
        }
      },
      "damage": {
        "parts": [
          {
            "value": {
              "dice": "d12",
              "bonus": 10,
              "multiplier": "prof",
              "flatMultiplier": 1,
              "custom": {
                "enabled": false,
                "formula": ""
              }
            },
            "type": [
              "physical"
            ],
            "applyTo": "hitPoints",
            "resultBased": false,
            "valueAlt": {
              "multiplier": "prof",
              "flatMultiplier": 1,
              "dice": "d6",
              "bonus": null,
              "custom": {
                "enabled": false,
                "formula": ""
              }
            },
            "base": false
          }
        ],
        "includeBase": false
      },
      "chatDisplay": true,
      "actionType": "action"
    },
    "actions": {
      "Reality Cut": {
        "type": "effect",
        "systemPath": "actions",
        "description": "<p></p><p><span style=\"font-family: 'Bruno Ace'\"><strong>Reality Cut:</strong></span></p><ul><li><p><span style=\"font-family: Montserrat, sans-serif\">Can slice vehicles, turrets, drones.</span></p></li></ul>",
        "chatDisplay": true,
        "actionType": "action",
        "cost": [],
        "uses": {
          "value": null,
          "max": "",
          "recovery": null,
          "consumeOnSuccess": false
        },
        "effects": [],
        "target": {
          "type": "any",
          "amount": null
        },
        "name": "Reality Cut",
        "img": "modules/cybermancy/assets/icons/features/reality-cut.webp",
        "range": ""
      },
      "Sever Reality": {
        "type": "effect",
        "systemPath": "actions",
        "description": "<p></p><p><span style=\"font-family: 'Bruno Ace'\"><strong>Critical Effect - Sever Reality:</strong></span></p><ul><li><p><span style=\"font-family: Montserrat, sans-serif\">Slice environment  create a permanent gap or hazard.</span></p></li></ul>",
        "chatDisplay": true,
        "actionType": "action",
        "cost": [],
        "uses": {
          "value": null,
          "max": "",
          "recovery": null,
          "consumeOnSuccess": false
        },
        "effects": [],
        "target": {
          "type": "any",
          "amount": null
        },
        "name": "Critical Effect:  Sever Reality",
        "img": "modules/cybermancy/assets/icons/features/sever-reality.webp",
        "range": ""
      }
    }
  },
  "effects": []
}